tradelocker/__about__.py
tradelocker/__init__.py
tradelocker/exceptions.py
tradelocker/py.typed
tradelocker/tradelocker_api.py
tradelocker/types.py
tradelocker/utils.py
tradelocker-0.56.2.dist-info/LICENSE.txt
tradelocker-0.56.2.dist-info/METADATA
tradelocker-0.56.2.dist-info/WHEEL
tradelocker-0.56.2.dist-info/RECORD
