Metadata-Version: 2.1
Name: tradelocker
Version: 0.56.2
Summary: Python client for TradeLocker's Trading API
License: MIT
Keywords: tradelocker,api,rest,trading,algotrading,algo,bots,strategies
Author: TradeLocker
Author-email: admin@tradelocker.com
Requires-Python: >=3.11
Classifier: License :: OSI Approved :: MIT License
Classifier: Programming Language :: Python :: 3
Classifier: Programming Language :: Python :: 3.11
Classifier: Programming Language :: Python :: 3.12
Requires-Dist: PyJWT (==2.8.0)
Requires-Dist: joblib (==1.4.2)
Requires-Dist: pandas (>=2.1.2)
Requires-Dist: python-dotenv (==1.0.0)
Requires-Dist: requests (==2.32.2)
Project-URL: Issues, https://github.com/tradelocker/tradelocker-python/issues
Project-URL: Source, https://github.com/tradelocker/tradelocker-python/
